{
  "tests": [
    {
      "name": "1",
      "setup": "make main",
      "run": "./main",
      "input": "5\r\n5 1 2 4 3",
      "output": "4",
      "comparison": "included",
      "timeout": 1,
      "points": 10
    },
    {
      "name": "2",
      "setup": "",
      "run": "./main",
      "input": "5\r\n2 3 1 4 5",
      "output": "2",
      "comparison": "included",
      "timeout": 1,
      "points": 10
    },
    {
      "name": "3",
      "setup": "",
      "run": "./main",
      "input": "1\r\n4",
      "output": "4",
      "comparison": "included",
      "timeout": 1,
      "points": 10
    },
    {
      "name": "4",
      "setup": "",
      "run": "./main",
      "input": "4\r\n1 2 3 4",
      "output": "3",
      "comparison": "included",
      "timeout": 1,
      "points": 10
    },
    {
      "name": "5",
      "setup": "",
      "run": "./main",
      "input": "7\r\n4 8 9 1 2 3 5",
      "output": "9",
      "comparison": "included",
      "timeout": 1,
      "points": 10
    },
    {
      "name": "6",
      "setup": "",
      "run": "./main",
      "input": "6\r\n2 3 4 5 1 6",
      "output": "4",
      "comparison": "included",
      "timeout": 1,
      "points": 10
    },
    {
      "name": "7",
      "setup": "",
      "run": "./main",
      "input": "2\r\n3 1",
      "output": "1",
      "comparison": "included",
      "timeout": 1,
      "points": 10
    },
    {
      "name": "8",
      "setup": "",
      "run": "./main",
      "input": "3\r\n2 5 1",
      "output": "2",
      "comparison": "included",
      "timeout": 1,
      "points": 10
    },
    {
      "name": "9",
      "setup": "",
      "run": "./main",
      "input": "10\r\n1 4 2 3 6 5 7 8 9 11",
      "output": "9",
      "comparison": "included",
      "timeout": 1,
      "points": 10
    },
    {
      "name": "10",
      "setup": "",
      "run": "./main",
      "input": "8\r\n1 3 4 5 10 11 2 4",
      "output": "4",
      "comparison": "included",
      "timeout": 1,
      "points": 10
    }
  ]
}